pymbt-0.0.2.dist-info/WHEEL
pymbt-0.0.2.dist-info/METADATA
pymbt-0.0.2.dist-info/DESCRIPTION.rst
pymbt-0.0.2.dist-info/metadata.json
pymbt-0.0.2.dist-info/top_level.txt
pymbt-0.0.2.dist-info/RECORD
pymbt/__init__.py
pymbt/reaction/_restriction.py
pymbt/reaction/_gibson.py
pymbt/reaction/__init__.py
pymbt/reaction/_central_dogma.py
pymbt/reaction/_oligo_assembly.py
pymbt/reaction/utils.py
pymbt/reaction/_pcr.py
pymbt/reaction/_resect.py
pymbt/analysis/__init__.py
pymbt/analysis/utils.py
pymbt/analysis/_sequencing/calign.c
pymbt/analysis/_sequencing/__init__.py
pymbt/analysis/_sequencing/calign.so
pymbt/analysis/_sequencing/align.py
pymbt/analysis/_sequencing/sanger.py
pymbt/analysis/_sequencing/needle.py
pymbt/analysis/_sequencing/data/__init__.py
pymbt/analysis/_sequencing/data/BLOSUM62
pymbt/analysis/_sequencing/data/__init__.pyc
pymbt/analysis/_sequencing/data/DNA_simple
pymbt/analysis/_sequencing/data/DNA
pymbt/analysis/_structure/structure_windows.py
pymbt/analysis/_structure/nupack.py
pymbt/analysis/_structure/__init__.py
pymbt/analysis/_structure/dimers.py
pymbt/analysis/_structure/vienna.py
pymbt/analysis/_sequence/__init__.py
pymbt/analysis/_sequence/melting_temp.py
pymbt/analysis/_sequence/repeats.py
pymbt/analysis/_sequence/tm_params.py
pymbt/seqio/__init__.py
pymbt/seqio/_dna.py
pymbt/sequence/__init__.py
pymbt/sequence/_peptide.py
pymbt/sequence/_rna.py
pymbt/sequence/_dna.py
pymbt/sequence/_sequence.py
pymbt/database/__init__.py
pymbt/database/_entrez.py
pymbt/database/_yeast.py
pymbt/database/_rebase.py
pymbt/design/_primers.py
pymbt/design/_gibson.py
pymbt/design/__init__.py
pymbt/design/_oligo_synthesis/__init__.py
pymbt/design/_oligo_synthesis/oligo_assembly.py
pymbt/design/_sequence_generation/__init__.py
pymbt/design/_sequence_generation/random_sequences.py
pymbt/constants/genbank.py
pymbt/constants/__init__.py
pymbt/constants/restriction_sites.py
pymbt/constants/molecular_bio.py
