Metadata-Version: 2.0
Name: pymbt
Version: 0.0.2
Summary: pymbt
Home-page: https://github.com/klavinslab/pymbt
Author: Nick Bolten
Author-email: nbolten _at_ gmail
License: Copyright University of Washington
Download-URL: https://github.com/klavinslab/pymbt.git
Platform: UNKNOWN
Requires-Dist: cython
Requires-Dist: nose
Requires-Dist: numpy
Requires-Dist: biopython
Requires-Dist: intermine
Requires-Dist: requests
Provides-Extra: documentation
Requires-Dist: sphinx; extra == 'documentation'
Provides-Extra: plotting
Requires-Dist: matplotlib; extra == 'plotting'
